aidkitHW
