Metadata-Version: 1.0
Name: aidkitHW
Version: 0.1.6
Summary: Python package for coding challenge
Home-page: https://github.com/hududed
Author: Hud Wahab
Author-email: hudwahab@gmail.com
License: Apache License 2.0
Platform: UNKNOWN
